fabricplus/__init__.py
fabricplus/connection.py
fabricplus/paramiko_modifications/__init__.py
fabricplus/paramiko_modifications/client.py
fabricplus/py.typed
fabricplus/transfer.py
fabricplus-1.0.1.dist-info/LICENSE
fabricplus-1.0.1.dist-info/METADATA
fabricplus-1.0.1.dist-info/WHEEL
fabricplus-1.0.1.dist-info/RECORD
