Metadata-Version: 2.1
Name: fabricplus
Version: 1.0.1
Summary: A Python 3.8.10+ wrapper to add in SCP functionality for file transfer in Fabric.
Home-page: https://fabricplus.prokopto.dev/
License: MIT
Keywords: fabric,scp,file transfer,python,wrapper,paramiko,connection,transfer
Author: Courtney Caldwell
Author-email: courtneyccaldwell@gmail.com
Maintainer: Courtney Caldwell
Maintainer-email: courtneyccaldwell@gmail.com
Requires-Python: >=3.8.1,<4.0
Classifier: License :: OSI Approved :: MIT License
Classifier: Operating System :: OS Independent
Classifier: Programming Language :: Python :: 3
Classifier: Programming Language :: Python :: 3.9
Classifier: Programming Language :: Python :: 3.10
Classifier: Programming Language :: Python :: 3.11
Classifier: Programming Language :: Python :: 3.12
Classifier: Programming Language :: Python :: 3.8
Classifier: Topic :: Software Development :: Libraries :: Python Modules
Classifier: Topic :: System :: Networking
Classifier: Topic :: System :: Systems Administration
Classifier: Topic :: Utilities
Requires-Dist: fabric (>=3.2.2,<4.0.0)
Requires-Dist: invoke (>=2.2.0,<3.0.0)
Requires-Dist: paramiko (>=3.4.0,<4.0.0)
Requires-Dist: scp (>=0.14.5,<0.15.0)
Project-URL: Repository, https://github.com/prokopto-dev/fabric-plus
